bookmark_lens/__init__.py
bookmark_lens/__main__.py
bookmark_lens/config.py
bookmark_lens/errors.py
bookmark_lens/server.py
bookmark_lens/database/__init__.py
bookmark_lens/database/duckdb_client.py
bookmark_lens/database/lancedb_client.py
bookmark_lens/handlers/__init__.py
bookmark_lens/handlers/bookmark_handlers.py
bookmark_lens/handlers/content_handlers.py
bookmark_lens/handlers/search_handlers.py
bookmark_lens/handlers/stats_handlers.py
bookmark_lens/models/__init__.py
bookmark_lens/models/bookmark.py
bookmark_lens/services/__init__.py
bookmark_lens/services/bookmark_service.py
bookmark_lens/services/content_fetcher.py
bookmark_lens/services/embedding_service.py
bookmark_lens/services/llm_service.py
bookmark_lens/services/search_service.py
bookmark_lens-0.0.8.dist-info/licenses/LICENSE
bookmark_lens-0.0.8.dist-info/METADATA
bookmark_lens-0.0.8.dist-info/WHEEL
bookmark_lens-0.0.8.dist-info/entry_points.txt
bookmark_lens-0.0.8.dist-info/top_level.txt
bookmark_lens-0.0.8.dist-info/RECORD
