Metadata-Version: 2.4
Name: bookmark-lens
Version: 0.0.8
Summary: Local-first MCP server for intelligent bookmark management with semantic search
Author-email: Corneliu Croitoru <your.email@example.com>
License: MIT
Project-URL: Homepage, https://github.com/yourusername/bookmark-lens
Project-URL: Repository, https://github.com/yourusername/bookmark-lens
Project-URL: Issues, https://github.com/yourusername/bookmark-lens/issues
Keywords: mcp,bookmarks,semantic-search,ai,embeddings,llm
Classifier: Development Status :: 4 - Beta
Classifier: Intended Audience :: Developers
Classifier: License :: OSI Approved :: MIT License
Classifier: Programming Language :: Python :: 3
Classifier: Programming Language :: Python :: 3.10
Classifier: Programming Language :: Python :: 3.11
Classifier: Programming Language :: Python :: 3.12
Classifier: Topic :: Software Development :: Libraries :: Python Modules
Classifier: Topic :: Internet :: WWW/HTTP :: Indexing/Search
Requires-Python: >=3.10
License-File: LICENSE
Requires-Dist: fastmcp>=2.9.0
Requires-Dist: duckdb>=0.9.0
Requires-Dist: lancedb>=0.3.0
Requires-Dist: pyarrow>=14.0.0
Requires-Dist: sentence-transformers>=2.2.0
Requires-Dist: torch>=2.0.0
Requires-Dist: numpy>=1.24.0
Requires-Dist: requests>=2.31.0
Requires-Dist: beautifulsoup4>=4.12.0
Requires-Dist: lxml>=4.9.0
Requires-Dist: lxml_html_clean>=0.1.0
Requires-Dist: readability-lxml>=0.8.1
Requires-Dist: markdownify>=0.11.0
Requires-Dist: pydantic>=2.0.0
Requires-Dist: pydantic-settings>=2.0.0
Requires-Dist: platformdirs>=3.0.0
Requires-Dist: uvloop>=0.19.0; platform_system != "Windows"
Provides-Extra: dev
Requires-Dist: pytest>=7.4.0; extra == "dev"
Requires-Dist: pytest-asyncio>=0.21.0; extra == "dev"
Requires-Dist: black>=23.0.0; extra == "dev"
Requires-Dist: ruff>=0.1.0; extra == "dev"
Requires-Dist: mypy>=1.5.0; extra == "dev"
Provides-Extra: ui
Requires-Dist: gradio>=4.0.0; extra == "ui"
Dynamic: license-file
